{
  "system-security-plan": {
    "uuid": "13e6733a-8efd-4fc4-81d6-fd19c09d6653",
    "metadata": {
      "title": "SSP (RoPA) – Template with Full Statements",
      "last-modified": "2025-11-01T07:03:02Z",
      "version": "0.3.1",
      "oscal-version": "1.1.2",
      "props": [
        { "name": "ui:preferred-viewer", "value": "https://viewer.oscal.io" },
        { "name": "ui:lang-default", "value": "de" }
      ],
      "parties": [
        { "uuid": "1e2a0a90-7a44-40fe-ba39-ef57f3b6e23b", "type": "organization", "name": "Controller (organisation)" },
        { "uuid": "8d6ff23c-7593-43eb-a24f-1b7be87c9d13", "type": "person", "name": "Data Protection Officer" },
        { "uuid": "b4648015-32ed-4930-ab27-efea825ed0d3", "type": "person", "name": "Information Security Officer / CISO" },
        { "uuid": "7ffa028e-13a9-43dd-b69e-868a8a21f594", "type": "person", "name": "Product Owner / Business Owner" }
      ]
    },
    "import-profile": {
      "href": "https://raw.githubusercontent.com/open-gov-group/opengov-privacy-oscal/main/oscal/profiles/profile_intervenability.json"
    },
    "system-characteristics": {
      "system-ids": [{ "identifier-type": "assigned", "id": "SSP-RoPA-XXX" }],
      "system-name": "Processing activity – <Title>",
      "system-name-short": "PA-<Short>",
      "description": "Short description of the processing, purpose, legal basis, categories of data subjects/data.",
      "status": { "state": "operational" },
      "security-sensitivity-level": "moderate",
      "system-information": {
        "information-types": [
          { "title": "Personal data (GDPR)", "description": "Typical RoPA categories (e.g., identification, contact, usage)." }
        ]
      },
      "props": [
        { "name": "ropa:purpose", "value": "<purpose(s)>" },
        { "name": "ropa:data-categories", "value": "<categories of personal data>" },
        { "name": "ropa:data-subjects", "value": "<data subject categories>" },
        { "name": "ropa:recipients", "value": "<recipients/categories>" },
        { "name": "ropa:third-country-transfers", "value": "<No/Yes – legal basis>" },
        { "name": "ropa:retention", "value": "<retention/erasure periods>" },
        { "name": "ropa:legal-basis", "value": "<Art. 6 GDPR / sector law>" }
      ]
    },
    "system-implementation": {
      "components": [
        {
          "uuid": "00000000-0000-0000-0000-00000000c0de",
          "type": "service",
          "title": "Rights Portal / IAM",
          "description": "Interface for data subject rights (SPOC, portal, APIs).",
          "status": { "state": "operational" }
        },
        {
          "uuid": "00000000-0000-0000-0000-00000000d0c2",
          "type": "software",
          "title": "Dokumentenmanagementsystem",
          "description": "Imported from component-definition",
          "status": { "state": "operational" }
        },
        {
          "uuid": "00000000-0000-0000-0000-00000000del1",
          "type": "service",
          "title": "Deletion Workflow",
          "description": "Imported from component-definition",
          "status": { "state": "operational" }
        },
        {
          "uuid": "00000000-0000-0000-0000-00000000bkp1",
          "type": "service",
          "title": "Backup/Restore Service",
          "description": "Imported from component-definition",
          "status": { "state": "operational" }
        }
      ]
    },
    "control-implementation": {
      "description": "Implementation of all profile-included controls; component mapping and parameterization.",
      "implemented-requirements": [
        {
          "uuid": "00000000-0000-0000-0000-00000000b101",
          "control-id": "B1-1",
          "statements": [
            {
              "statement-id": "B1-1_stmt",
              "uuid": "00000000-0000-0000-0000-00000000b1a1",
              "by-components": [
                {
                  "component-uuid": "00000000-0000-0000-0000-00000000c0de",
                  "uuid": "00000000-0000-0000-0000-00000000b1b1",
                  "description": "Transparenz & Informationspflichten: veröffentlichte Datenschutzhinweise, leicht zugängliche Auskunftskanäle, Benachrichtigungen.",
                  "set-parameters": [
                    { "param-id": "B1-1_prm_1", "values": ["<public privacy notice URL>"] },
                    { "param-id": "B1-1_prm_2", "values": ["<SLA for responses>"] }
                  ]
                },
                {
                  "component-uuid": "00000000-0000-0000-0000-00000000d0c2",
                  "uuid": "00000000-0000-0000-0000-00000000b1b2",
                  "description": "DMS stellt publizierte Hinweise & Aktenplankontext bereit."
                }
              ]
            }
          ]
        },
        {
          "uuid": "00000000-0000-0000-0000-00000000b102",
          "control-id": "B1-2",
          "statements": [
            {
              "statement-id": "B1-2_stmt",
              "uuid": "00000000-0000-0000-0000-00000000b2a1",
              "by-components": [
                {
                  "component-uuid": "00000000-0000-0000-0000-00000000c0de",
                  "uuid": "00000000-0000-0000-0000-00000000b2b1",
                  "description": "Zweckbindung & Zwecktrennung: IAM-Rollen/Scopes."
                },
                {
                  "component-uuid": "00000000-0000-0000-0000-00000000d0c2",
                  "uuid": "00000000-0000-0000-0000-00000000b2b2",
                  "description": "DMS erzwingt Zweckmetadaten / Mandantentrennung."
                }
              ]
            }
          ]
        },
        {
          "uuid": "00000000-0000-0000-0000-00000000b103",
          "control-id": "B1-3",
          "statements": [
            {
              "statement-id": "B1-3_stmt",
              "uuid": "00000000-0000-0000-0000-00000000b3a1",
              "by-components": [
                {
                  "component-uuid": "00000000-0000-0000-0000-00000000c0de",
                  "uuid": "00000000-0000-0000-0000-00000000b3b1",
                  "description": "Pseudonymisierung/Maskierung in Portal/Logs."
                },
                {
                  "component-uuid": "00000000-0000-0000-0000-00000000del1",
                  "uuid": "00000000-0000-0000-0000-00000000b3b2",
                  "description": "Lösch-Engine: Pre-Delete Minimierung wo zulässig."
                }
              ]
            }
          ]
        },
        {
          "uuid": "00000000-0000-0000-0000-00000000b106",
          "control-id": "B1-6",
          "statements": [
            {
              "statement-id": "B1-6_stmt",
              "uuid": "00000000-0000-0000-0000-00000000b6a1",
              "by-components": [
                {
                  "component-uuid": "00000000-0000-0000-0000-00000000d0c2",
                  "uuid": "00000000-0000-0000-0000-00000000b6b1",
                  "description": "DMS nutzt WORM/Hash & Versionierung."
                }
              ]
            }
          ]
        },
        {
          "uuid": "00000000-0000-0000-0000-00000000b107",
          "control-id": "B1-7",
          "statements": [
            {
              "statement-id": "B1-7_stmt",
              "uuid": "00000000-0000-0000-0000-00000000b7a1",
              "by-components": [
                {
                  "component-uuid": "00000000-0000-0000-0000-00000000c0de",
                  "uuid": "00000000-0000-0000-0000-00000000b7b1",
                  "description": "RBAC/ABAC, MFA, crypto-in-transit/rest."
                },
                {
                  "component-uuid": "00000000-0000-0000-0000-00000000bkp1",
                  "uuid": "00000000-0000-0000-0000-00000000b7b2",
                  "description": "Backups verschlüsselt, Key-Rotation via KMS."
                }
              ]
            }
          ]
        },
        {
          "uuid": "00000000-0000-0000-0000-00000000b108",
          "control-id": "B1-8",
          "statements": [
            {
              "statement-id": "B1-8_stmt",
              "uuid": "00000000-0000-0000-0000-00000000b8a1",
              "by-components": [
                {
                  "component-uuid": "00000000-0000-0000-0000-00000000d0c2",
                  "uuid": "00000000-0000-0000-0000-00000000b8b1",
                  "description": "DMS: Audit-Logs, Versionierung, Aktenplan-ID Link."
                }
              ]
            }
          ]
        },
        {
          "uuid": "00000000-0000-0000-0000-00000000b110",
          "control-id": "B1-10",
          "statements": [
            {
              "statement-id": "B1-10_stmt",
              "uuid": "00000000-0000-0000-0000-00000000b10a",
              "by-components": [
                {
                  "component-uuid": "00000000-0000-0000-0000-00000000c0de",
                  "uuid": "00000000-0000-0000-0000-00000000b10b",
                  "description": "SPOC/Portal/API, AuthN/Z, SLA-Tracking, Export/Löschung.",
                  "set-parameters": [
                    { "param-id": "B1-10_prm_1", "values": ["<SPOC/team/role>"] },
                    { "param-id": "B1-10_prm_2", "values": ["<response SLA (e.g., 1 month)>"] }
                  ]
                }
              ]
            }
          ]
        },
        {
          "uuid": "00000000-0000-0000-0000-00000000b112",
          "control-id": "B1-12",
          "statements": [
            {
              "statement-id": "B1-12_stmt",
              "uuid": "00000000-0000-0000-0000-00000000b12a",
              "by-components": [
                {
                  "component-uuid": "00000000-0000-0000-0000-00000000del1",
                  "uuid": "00000000-0000-0000-0000-00000000b12b",
                  "description": "Lösch-Engine erzeugt Erasure Proof; Reporting.",
                  "set-parameters": [
                    { "param-id": "B1-12_prm_1", "values": ["<retention policy>"] },
                    { "param-id": "B1-12_prm_2", "values": ["<erasure proof mechanism>"] }
                  ]
                }
              ]
            }
          ]
        },
        {
          "uuid": "00000000-0000-0000-0000-00000000b114",
          "control-id": "B1-14",
          "statements": [
            {
              "statement-id": "B1-14_stmt",
              "uuid": "00000000-0000-0000-0000-00000000b14a",
              "by-components": [
                {
                  "component-uuid": "00000000-0000-0000-0000-00000000c0de",
                  "uuid": "00000000-0000-0000-0000-00000000b14b",
                  "description": "Export in strukturierten Formaten über das Portal/IAM.",
                  "set-parameters": [
                    { "param-id": "B1-14_prm_1", "values": ["<export format(s)>"] },
                    { "param-id": "B1-14_prm_2", "values": ["<export endpoint/process>"] }
                  ]
                }
              ]
            }
          ]
        },
        {
          "uuid": "00000000-0000-0000-0000-00000000b120",
          "control-id": "B1-20",
          "statements": [
            {
              "statement-id": "B1-20_stmt",
              "uuid": "00000000-0000-0000-0000-00000000b20a",
              "by-components": [
                {
                  "component-uuid": "00000000-0000-0000-0000-00000000bkp1",
                  "uuid": "00000000-0000-0000-0000-00000000b20b",
                  "description": "RTO/RPO definiert; regelmäßige Restore-Tests & Nachweise.",
                  "set-parameters": [
                    { "param-id": "B1-20_prm_1", "values": ["<RTO hours>"] },
                    { "param-id": "B1-20_prm_2", "values": ["<RPO minutes>"] }
                  ]
                }
              ]
            }
          ]
        }
      ]
    },
    "back-matter": {
      "resources": [
        {
          "uuid": "res-ruleset-xdomea",
          "title": "XDOMEA → RoPA Default Mapping",
          "rlinks": [
            {
              "href": "https://raw.githubusercontent.com/open-gov-group/opengov-privacy-app/main/mappings/xdomea_to_ropa.yaml",
              "media-type": "text/yaml"
            }
          ]
        },        
        {
          "uuid": "res-profile",
          "title": "Profile (source)",
          "rlinks": [
            {
              "href": "https://raw.githubusercontent.com/open-gov-group/opengov-privacy-oscal/main/oscal/profiles/profile_intervenability.json",
              "media-type": "application/json"
            }
          ]
        },
        {
          "uuid": "res-profile-resolved",
          "title": "Profile (resolved)",
          "rlinks": [
            {
              "href": "https://raw.githubusercontent.com/open-gov-group/opengov-privacy-oscal/main/build/profile_resolved_catalog.json",
              "media-type": "application/json"
            }
          ]
        },
        {
          "uuid": "res-catalog",
          "title": "Catalog",
          "rlinks": [
            {
              "href": "https://raw.githubusercontent.com/open-gov-group/opengov-privacy-oscal/main/oscal/catalog/opengov_privacy_catalog.json",
              "media-type": "application/json"
            }
          ]
        },
        {
          "uuid": "res-risk-qual",
          "title": "Risk Matrix (qualitative)",
          "rlinks": [
            {
              "href": "https://raw.githubusercontent.com/open-gov-group/opengov-privacy-oscal/main/resources/risk/qualitative.csv",
              "media-type": "text/csv"
            }
          ]
        },
        {
          "uuid": "res-risk-quant",
          "title": "Risk Matrix (quantitative)",
          "rlinks": [
            {
              "href": "https://raw.githubusercontent.com/open-gov-group/opengov-privacy-oscal/main/resources/risk/quantitative.json",
              "media-type": "application/json"
            }
          ]
        },
        {
          "uuid": "res-i18n-de",
          "title": "UI Strings (DE)",
          "rlinks": [
            {
              "href": "https://raw.githubusercontent.com/open-gov-group/opengov-privacy-oscal/main/resources/i18n/de.json",
              "media-type": "application/json"
            }
          ]
        },
        {
          "uuid": "res-i18n-en",
          "title": "UI Strings (EN)",
          "rlinks": [
            {
              "href": "https://raw.githubusercontent.com/open-gov-group/opengov-privacy-oscal/main/resources/i18n/en.json",
              "media-type": "application/json"
            }
          ]
        }
      ]
    }
  }
}
